downscale_image/__init__.py
downscale_image/__main__.py
downscale_image/_registry_utils.py
LICENSE
downscale_image-1.4.4.dist-info/entry_points.txt
downscale_image-1.4.4.dist-info/LICENSE
downscale_image-1.4.4.dist-info/WHEEL
downscale_image-1.4.4.dist-info/METADATA
downscale_image-1.4.4.dist-info/RECORD
