Metadata-Version: 2.1
Name: downscale-image
Version: 1.4.4
Summary: downscale image to desired file size
Home-page: https://github.com/mshafer1/downscale_image
License: MIT
Author: mshafer1
Requires-Python: >=3.7,<4.0
Classifier: License :: OSI Approved :: MIT License
Classifier: Programming Language :: Python :: 3
Classifier: Programming Language :: Python :: 3.7
Classifier: Programming Language :: Python :: 3.8
Classifier: Programming Language :: Python :: 3.9
Requires-Dist: click (>=8.0)
Requires-Dist: pathspec (>=0.10.1,<0.11.0)
Requires-Dist: tqdm (>=4.65.0,<5.0.0)
Project-URL: Repository, https://github.com/mshafer1/downscale_image
